{


  "C1heading" :  "FLEX TRAVEL CARD",
  "C2heading" : "BLACK PREMIUM CARD",
  "C3heading" : "GOLDEN APB CARD",
  "C1detail" : "Enjoy the benefit of travelling with our FLEX TRAVEL CARD. Book tickets and get rewards.",
  "C2detail" : "With our BLACK PREMIUM CARD, get an effective discount on every product you buy with it.",
  "C3detail" : "The GOLDNE APB CARD all you need for everything. Use and get effective discount and rewards.",
  "C1smdetails":"BEST FOR USING IN TRAVELLING",
  "C2smdetails":"BEST FOR PRODUCTS SHOPING",
  "C3smdetails":"ALL IN ONE BEST CARD",
  "Apply":"Apply"

  
 

}


